{
  "schema_version": "1.0",
  "updated_at": "2026-04-30",
  "filters": {
    "industries": [
      "제조업",
      "지식서비스업",
      "게임개발업"
    ],
    "types": [
      "R&D",
      "창업",
      "판로수출",
      "인력",
      "정책자금",
      "인증",
      "투자유치"
    ]
  },
  "programs": [
    {
      "id": "01",
      "file": "01-gyeonggi-promising-sme.html",
      "title": "2026년 경기도 유망중소기업 선정계획",
      "summary": "경기도 내 본사 또는 등록공장 보유 중소기업 대상 인증사업. 200개사 (신규 165 + 재인증 35). 9개 기관 63개 혜택.",
      "tags": [
        "인증사업",
        "경기도",
        "GBSA"
      ],
      "industries": [
        "제조업",
        "지식서비스업",
        "게임개발업"
      ],
      "types": [
        "인증"
      ],
      "deadline_iso": "2026-04-30T17:00:00+09:00",
      "deadline_display": "4.30(목) 17:00",
      "meta": {
        "지원": "5년 인증 + 5백만원",
        "혜택": "가점·금리·보증",
        "마감": "4.30(목) 17:00"
      }
    },
    {
      "id": "02",
      "file": "02-small-business-leap.html",
      "title": "2026년 소상공인 도약 지원 사업",
      "summary": "로컬기업 육성 + 강한소상공인 성장지원 통합. 강한 혁신 유형은 국비 100% (자부담 0). 사업화 1억원 한도.",
      "tags": [
        "소상공인",
        "통합공고",
        "소진공"
      ],
      "industries": [
        "제조업"
      ],
      "types": [
        "판로수출"
      ],
      "deadline_iso": "2026-05-06T16:00:00+09:00",
      "deadline_display": "5.6(수) 16:00",
      "meta": {
        "지원": "최대 1억원",
        "비율": "80~100%",
        "마감": "5.6(수) 16:00"
      }
    },
    {
      "id": "03",
      "file": "03-export-voucher.html",
      "title": "2026년 수출바우처 사업 2차 모집",
      "summary": "5개 수출 트랙(내수~수출강소). 패스트트랙 도입으로 1개월 내 선정. 해외인증·물류·풀필먼트 신설 항목 확대.",
      "tags": [
        "수출 · 바우처",
        "2차 모집",
        "중소벤처기업부"
      ],
      "industries": [
        "제조업",
        "지식서비스업",
        "게임개발업"
      ],
      "types": [
        "판로수출"
      ],
      "deadline_iso": "2026-05-06T17:00:00+09:00",
      "deadline_display": "5.6(수) 17:00",
      "meta": {
        "지원": "최대 1억원",
        "비율": "50~70%",
        "마감": "5.6(수) 17:00"
      }
    },
    {
      "id": "04",
      "file": "04-overseas-cert.html",
      "title": "2026년 해외규격인증 추경 추가지원",
      "summary": "578개 해외규격인증의 인증비·시험비·컨설팅비 50~70%. 360개사 내외. 중동 22개국 수출이력 보유 시 우선선정.",
      "tags": [
        "수출 · 인증",
        "추경 추가지원",
        "중소벤처기업부"
      ],
      "industries": [
        "제조업"
      ],
      "types": [
        "판로수출"
      ],
      "deadline_iso": "2026-05-29T18:00:00+09:00",
      "deadline_display": "5.29(금) 18:00",
      "meta": {
        "지원": "최대 1억원",
        "비율": "50~70%",
        "마감": "5.29(금) 18:00"
      }
    },
    {
      "id": "05",
      "file": "05-hi-seoul.html",
      "title": "2026년 하이서울기업 인증 신규 모집",
      "summary": "서울시 소재 중소기업 100개사 인증. 정량(30) + 서류(30) + 발표(40) 3단계 평가. BI 사용권 + SBA 가점.",
      "tags": [
        "인증사업",
        "서울시",
        "SBA"
      ],
      "industries": [
        "제조업",
        "지식서비스업",
        "게임개발업"
      ],
      "types": [
        "인증"
      ],
      "deadline_iso": "2026-05-08T18:00:00+09:00",
      "deadline_display": "5.8(금) 18:00",
      "meta": {
        "지원": "3년 인증 + 가점",
        "혜택": "B2B·글로벌",
        "마감": "5.8(금) 18:00"
      }
    },
    {
      "id": "06",
      "file": "06-knock-pitching.html",
      "title": "2026 콘텐츠 피칭 KNOCK 정규라운드",
      "summary": "콘텐츠 9개 분야 법인 20개사. 매출 5억 또는 누적투자 10억. 10개 파트너 VC 매칭 + IR 컨설팅 + 상금 5천만원.",
      "tags": [
        "콘텐츠 · 투자유치",
        "VC 매칭",
        "콘텐츠진흥원"
      ],
      "industries": [
        "지식서비스업",
        "게임개발업"
      ],
      "types": [
        "투자유치"
      ],
      "deadline_iso": "2026-05-08T14:00:00+09:00",
      "deadline_display": "5.8(금) 14:00",
      "meta": {
        "지원": "VC 매칭 + 상금",
        "형태": "민간 투자유치",
        "마감": "5.8(금) 14:00"
      }
    },
    {
      "id": "07",
      "file": "07-tech-commercialization.html",
      "title": "2026년 기술사업화 패키지 2차",
      "summary": "정부 R&D 우수과제·기술이전·규제혁신·R&D 창업 4개 트랙. 사업화 전담기관 처방 → 메뉴판 서비스 구매·정산.",
      "tags": [
        "R&D 사업화",
        "4개 트랙",
        "중소벤처기업부"
      ],
      "industries": [
        "제조업",
        "지식서비스업",
        "게임개발업"
      ],
      "types": [
        "R&D",
        "판로수출"
      ],
      "deadline_iso": "2026-05-26T18:00:00+09:00",
      "deadline_display": "5.26(화) 18:00",
      "meta": {
        "지원": "최대 1.5억원",
        "비율": "40~60%",
        "마감": "5.26(화) 18:00"
      }
    },
    {
      "id": "08",
      "file": "08-oi-midcap-startup.html",
      "title": "2026년 민관협력 OI 중견-스타트업",
      "summary": "중견기업·중소기업 졸업유예가 협업 과제 제출. 매칭된 스타트업에 1.4억원 + 디딤돌·구매연계형 후속 6억 연계.",
      "tags": [
        "오픈이노베이션",
        "중견-스타트업",
        "중소벤처기업부"
      ],
      "industries": [
        "지식서비스업"
      ],
      "types": [
        "R&D",
        "창업"
      ],
      "deadline_iso": "2026-05-11T16:00:00+09:00",
      "deadline_display": "5.11(월) 16:00",
      "meta": {
        "지원": "스타트업 1.4억",
        "분야": "13개 전략기술",
        "마감": "5.11(월) 16:00"
      }
    },
    {
      "id": "09",
      "file": "09-product-allinone.html",
      "title": "2026년 제품화 올인원팩",
      "summary": "제조 분야 창업 7년 이내 80개사. 설계~초도양산 원스톱. 6개 주관기관 1개 선택. 자부담 30% 현금 매칭 필수.",
      "tags": [
        "창업 · 제조",
        "권역별 주관",
        "중소벤처기업부"
      ],
      "industries": [
        "제조업"
      ],
      "types": [
        "창업",
        "R&D"
      ],
      "deadline_iso": "2026-05-11T16:00:00+09:00",
      "deadline_display": "5.11(월) 16:00",
      "meta": {
        "지원": "최대 5천만원",
        "비율": "70%",
        "마감": "5.11(월) 16:00"
      }
    },
    {
      "id": "10",
      "file": "10-uknock-japan.html",
      "title": "U-KNOCK 2026 in Japan",
      "summary": "IP·엔터 콘텐츠 10개사 도쿄 현지 IR. 매출 10억+해외 5억 또는 누적투자 20억. 일본어 발표·항공비 지원.",
      "tags": [
        "콘텐츠 · 해외 IR",
        "일본 진출",
        "콘텐츠진흥원"
      ],
      "industries": [
        "지식서비스업",
        "게임개발업"
      ],
      "types": [
        "투자유치"
      ],
      "deadline_iso": "2026-05-11T14:00:00+09:00",
      "deadline_display": "5.11(월) 14:00",
      "meta": {
        "지원": "현지 IR + 항공비",
        "일정": "7.7~7.10 도쿄",
        "마감": "5.11(월) 14:00"
      }
    },
    {
      "id": "11",
      "file": "11-k-soshangoeng.html",
      "title": "2026년 글로벌 소상공인 (K-소상공인)",
      "summary": "4대 소비재(식품·화장품·패션·생활용품) 100개사. 旣 지원/민간 투자/수출 3만달러 中 1개. 글로벌 오디션 차등.",
      "tags": [
        "소상공인 · 수출",
        "글로벌 진출",
        "소진공"
      ],
      "industries": [
        "제조업"
      ],
      "types": [
        "창업",
        "판로수출"
      ],
      "deadline_iso": "2026-05-15T16:00:00+09:00",
      "deadline_display": "5.15(금) 16:00",
      "meta": {
        "지원": "최대 1억원",
        "형태": "로컬+혁신 트랙",
        "마감": "5.15(금) 16:00"
      }
    },
    {
      "id": "12",
      "file": "12-oi-mutual-explore.html",
      "title": "2026년 민관협력 OI 자율탐색형 (스타트업)",
      "summary": "스타트업 7년 이내 50개사. 6대 전략산업 12대 신산업 분야. OI 마켓 자율매칭 → 협업제안서 → 최종선정.",
      "tags": [
        "오픈이노베이션",
        "자율탐색형",
        "중소벤처기업부"
      ],
      "industries": [
        "제조업",
        "지식서비스업",
        "게임개발업"
      ],
      "types": [
        "R&D",
        "창업"
      ],
      "deadline_iso": "2026-05-18T16:00:00+09:00",
      "deadline_display": "5.18(월) 16:00",
      "meta": {
        "지원": "최대 1억원",
        "분야": "AI·Bio·Defence 등",
        "마감": "5.18(월) 16:00"
      }
    },
    {
      "id": "13",
      "file": "13-motie-emergency-voucher.html",
      "title": "[추경] 2026년 산업통상부 긴급지원바우처 3차",
      "summary": "중동전쟁 영향 수출 중소·중견기업 긴급지원. 운영기관 KOTRA. 5.6 마감 중기부 수출바우처 2차로 대체 검토 가능.",
      "tags": [
        "수출 · 바우처",
        "긴급지원 3차",
        "산업통상부"
      ],
      "industries": [
        "제조업",
        "지식서비스업",
        "게임개발업"
      ],
      "types": [
        "판로수출"
      ],
      "deadline_iso": "2026-04-26T18:00:00+09:00",
      "deadline_display": "4.26(일) 종료",
      "meta": {
        "지원": "긴급바우처",
        "완료": "~26.11.30",
        "마감": "4.26(일) 종료"
      }
    },
    {
      "id": "14",
      "file": "14-govtech-ai.html",
      "title": "2026년 GovTech 창업기업 AI 실증·사업화",
      "summary": "7년 이내 창업기업 + 수요기관(정부·공공) 컨소시엄 18개 과제. 과제당 최대 1.8억원. NIPA 운영.",
      "tags": [
        "AI · 공공혁신",
        "컨소시엄",
        "과기정통부"
      ],
      "industries": [
        "지식서비스업"
      ],
      "types": [
        "R&D",
        "창업"
      ],
      "deadline_iso": "2026-04-23T16:00:00+09:00",
      "deadline_display": "4.23(목) 종료",
      "meta": {
        "지원": "과제당 1.8억",
        "비율": "75%",
        "마감": "4.23(목) 종료"
      }
    },
    {
      "id": "15",
      "file": "15-game-investment.html",
      "title": "2026년 게임기업 투자유치 지원사업",
      "summary": "경기도 내 게임기업 20개사. 1단계 IR 컨설팅·번역 + 2단계 10개사 데모데이 + 후속 게임쇼 부스 지원.",
      "tags": [
        "게임 · 투자유치",
        "경기도",
        "경기콘텐츠진흥원"
      ],
      "industries": [
        "게임개발업"
      ],
      "types": [
        "투자유치"
      ],
      "deadline_iso": "2026-04-23T15:00:00+09:00",
      "deadline_display": "4.23(목) 종료",
      "meta": {
        "지원": "IR 컨설팅 + 데모데이",
        "단계": "1단계 20 / 2단계 10",
        "마감": "4.23(목) 종료"
      }
    },
    {
      "id": "16",
      "file": "16-k-beauty-loan.html",
      "title": "2026년 중소기업 K-뷰티론 정책자금",
      "summary": "화장품 브랜드사 발주기반 융자. 발주(추천)서 또는 발주 증빙. 1회 최대 1.5억원, 12개월 내 생산 가능 제품 한정.",
      "tags": [
        "정책자금 · 화장품",
        "발주기반 융자",
        "중소벤처기업부"
      ],
      "industries": [
        "제조업"
      ],
      "types": [
        "정책자금"
      ],
      "deadline_iso": "2026-12-31T18:00:00+09:00",
      "deadline_display": "예산 소진시까지 (수시)",
      "meta": {
        "지원": "최대 1.5억원",
        "예산": "400억원",
        "마감": "예산 소진시까지"
      }
    },
    {
      "id": "17",
      "file": "17-tips.html",
      "title": "2026년 팁스(TIPS) 창업기업 지원계획",
      "summary": "팁스 운영사 2억+ 투자·추천 받은 창업 7년 이내 기업. R&D 일반 8억/딥테크 15억. 분기별 1회 접수.",
      "tags": [
        "R&D · 투자유치",
        "팁스 운영사",
        "중소벤처기업부"
      ],
      "industries": [
        "제조업",
        "지식서비스업",
        "게임개발업"
      ],
      "types": [
        "R&D",
        "창업",
        "투자유치"
      ],
      "deadline_iso": "2026-12-31T18:00:00+09:00",
      "deadline_display": "분기별 접수 (1·2·3분기)",
      "meta": {
        "지원": "일반 8억 / 딥테크 15억",
        "예산": "R&D 1,624억",
        "마감": "분기별 접수"
      }
    },
    {
      "id": "18",
      "file": "18-startup-leap.html",
      "title": "2026년 창업도약패키지 (일반형)",
      "summary": "도약기 창업기업(3~7년) 300개사. 사업화 자금 최대 2억원. 12개 권역 주관기관 1개 선택. 지방우대 자부담 차등.",
      "tags": [
        "창업 · 도약기",
        "권역별 주관",
        "중소벤처기업부"
      ],
      "industries": [
        "제조업",
        "지식서비스업",
        "게임개발업"
      ],
      "types": [
        "창업"
      ],
      "deadline_iso": "2026-02-13T16:00:00+09:00",
      "deadline_display": "2.13(금) 종료",
      "meta": {
        "지원": "최대 2억원",
        "비율": "70~90%",
        "마감": "2.13(금) 종료"
      }
    },
    {
      "id": "19",
      "file": "19-startup-initial.html",
      "title": "2026년 초기창업패키지 (일반형)",
      "summary": "창업 3년 이내 초기창업기업 400개사. 사업화 자금 최대 1억원. 17개 주관기관 권역별. 예비창업자는 정부 100%.",
      "tags": [
        "창업 · 초기",
        "권역별 주관",
        "중소벤처기업부"
      ],
      "industries": [
        "제조업",
        "지식서비스업",
        "게임개발업"
      ],
      "types": [
        "창업"
      ],
      "deadline_iso": "2026-02-13T16:00:00+09:00",
      "deadline_display": "2.13(금) 종료",
      "meta": {
        "지원": "최대 1억원",
        "비율": "70~90%",
        "마감": "2.13(금) 종료"
      }
    },
    {
      "id": "20",
      "file": "20-startup-univ.html",
      "title": "2026년 창업중심대학 지역기반",
      "summary": "예비~창업 7년 이내 535개사. 6개 권역 창업중심대학 중 1개 선택. 사업화 자금 최대 1억원 + 대학별 프로그램.",
      "tags": [
        "창업 · 대학",
        "지역기반",
        "중소벤처기업부"
      ],
      "industries": [
        "제조업",
        "지식서비스업",
        "게임개발업"
      ],
      "types": [
        "창업"
      ],
      "deadline_iso": "2026-03-23T16:00:00+09:00",
      "deadline_display": "3.23(월) 종료",
      "meta": {
        "지원": "최대 1억원",
        "선정": "535개사",
        "마감": "3.23(월) 종료"
      }
    },
    {
      "id": "21",
      "file": "21-research-staff.html",
      "title": "2026년 중소기업 연구인력지원사업",
      "summary": "기업부설연구소·전담부서 보유 중소기업. 신진·고경력 채용 + 공공연 파견 + 양성. 신규 775개 과제, 기준연봉 40~50%.",
      "tags": [
        "인력 · R&D",
        "4개 트랙",
        "중소벤처기업부"
      ],
      "industries": [
        "제조업",
        "지식서비스업",
        "게임개발업"
      ],
      "types": [
        "인력",
        "R&D"
      ],
      "deadline_iso": "2026-03-06T18:00:00+09:00",
      "deadline_display": "3.6(금) 종료",
      "meta": {
        "지원": "기준연봉 40~50%",
        "기간": "최대 3년",
        "마감": "3.6(금) 종료"
      }
    },
    {
      "id": "22",
      "file": "22-overseas-cert-strategy.html",
      "title": "2026년 해외규격인증 전략지원",
      "summary": "전략인증 9종(FDA·FCC·CE·CPNP·HALAL 등) + 고비용·의료기기 인증. 600개사 내외, 1.30~11.30 상시 모집.",
      "tags": [
        "수출 · 인증",
        "전략지원",
        "중소벤처기업부"
      ],
      "industries": [
        "제조업"
      ],
      "types": [
        "판로수출"
      ],
      "deadline_iso": "2026-11-30T18:00:00+09:00",
      "deadline_display": "11.30(월) 18:00 (상시)",
      "meta": {
        "지원": "최대 1억원",
        "비율": "50~70%",
        "마감": "상시 (~11.30)"
      }
    },
    {
      "id": "23",
      "file": "23-lips.html",
      "title": "2026년 소상공인 LIPS 프로그램",
      "summary": "민간 운영사 투자 받은 업력 1년+ 소상공인. LIPSⅠ 매칭융자 5억 / LIPSⅡ 시드립스 1억·스케일업 2억.",
      "tags": [
        "소상공인 · 투자유치",
        "LIPS Ⅰ·Ⅱ",
        "소진공"
      ],
      "industries": [
        "제조업"
      ],
      "types": [
        "정책자금",
        "투자유치"
      ],
      "deadline_iso": "2026-12-31T18:00:00+09:00",
      "deadline_display": "예산 소진시까지 (수시)",
      "meta": {
        "지원": "LIPSⅠ 5억 / LIPSⅡ 2억",
        "예산": "660억원",
        "마감": "예산 소진시까지"
      }
    }
  ]
}